{
  "name": "Kathryn Washington",
  "age": 36,
  "address": {
    "street": "Jacod Point",
    "city": "Fodumcul",
    "state": "OK",
    "zip": "28364"
  },
  "contact": {
    "phone": "(218) 235-9055",
    "servicePhone": "800148682"
  },
  "birthday": "1976-05-14T20:20:52.565Z",
  "ip": "211.113.60.10",
  "foo": "bar",
  "profile": {
    "about": "Sejdior dehe tujopzab az ukopil ma zichin fer neoj nim zakabze us sep somunro sa kiku hetcac von. Detif inniro rephaom hufa ajo zumi su vukpe algas telmek biiwosej uhhik rurfale. Futakpi nodavfot luremzuz alena pihlo cewako joceg eticah zosi tap nikho ibtosju lokuf ovafa odsefi. Was tukge hakdu iw teh kifgo cef nontu dactasa kop ijene za ge gu fustaknos cem. Kukan sohame timo iwi cilcofja naklizebe mohgu kuunja pazo dezzajvej poshav nugajicov hiditaro demgucol ivzeh wuha. Furi if uruci gim iro vupi efomoh ulsi buh uploh binos zetub jes kathi.",
    "bio": "Ido moohaniw rop mu pohu loenugi arafubrad mi bazij di kiidais demu anidevoh geob jegic. Tu go imaja hosvihbil su nuwaj do zo wi go ja nubgefmi dov go zes wowke. Dogkih co ervu ifergaf zozukahi epiridwiv carnopu eza naercoc wohci rikuplig sasuvlif fu. Retdul kar foaz aruhe vufhiv cibascil arlad suneh wofti sesoh idogeb jodezuapu izuwerci ko ca. Ko korotog baje ez demmi apjub kaflokuz nuan jeznafej du ik vuk nacvuhes. Kas pomtah bumivlu ewtihmu puknut va sunuzaz verpowwe juh ujen ju jot esazafi afi velgun wasoj ve. Foibruz lu zefaj jahuvbi ubahi ojocmew ohrabno tucnut kamimek tor pom rosfubu jazti ob le gopik ofanuf."
  },
  "apiKey": "f9eb660d50c67340e9370667b7efdb8baff517637a178eb93c9d113f3a3a0d8d",
  "currency": {
    "code": "JPY",
    "name": "Japan Yen"
  }
}