{
  "name": "Amanda Mills",
  "age": 20,
  "address": {
    "street": "Alobip Trail",
    "city": "Duhzenis",
    "state": "MD",
    "zip": "89117"
  },
  "contact": {
    "phone": "(440) 959-2439",
    "servicePhone": "800232248"
  },
  "birthday": "1967-08-21T06:40:07.800Z",
  "ip": "26.161.33.151",
  "foo": "bar",
  "profile": {
    "about": "Depapvu vodosanu buw ce wuwot ajuzaece ilebotih so raip ripzamoh eroag zagiv papku cakawme vogij bukje ijo. Kosal jepofufo jebenop hohade oko rojbac ca ubevojor ur kijugrid dezifup wewzovake fe cijubma. Apuejiwa lerjatis boeciut bi uteegori gijote jomvise jazsuw lusanle pe lipbev utha kis jalisir obo gedor. Igjoho sivjir ka tu hi aw ijmig vew gardus leni ke oj as udgezhes ronoumi asgeb uvo av. Il wozrotaso fojrec anwakar jahrec eto tek ko bu horeake nale kordaniw uwa meuponu veapulu aledog.",
    "bio": "Hu ticeznud fincecuc it ekehe tulnuzne da peik zoma mew wew jeim pa kuj. Sip em tic uwaol cakpihew ogobeko invoco bepidfa para ra givnu zu cil pokavlab emiva nobub. Etmirlis ohciv hivad sos fejbom uhnonlit fen sucje kuv izasi jubewe sero kochibap uz zul muga tadpah. Jivoso vizavok fin pa cah sulkilo nurji lor lupwik ef nor kodoh coah. Wu topozciz lubheh hu mowkemeci ir jedaw kabnuwa kop cuwpimna leh unisegak zas kiafu ececeeve bi. Wafpokid zot wedah pujet ju ladaf zu naded zecroz furmacbar tolag geskas taedu utuajeba egcuc mu sukjilfus jor."
  },
  "apiKey": "0e54500cc7f35ff10a0065125fff7048eb0da0b64881ec2972547b1682395411",
  "currency": {
    "code": "HNL",
    "name": "Honduras Lempira"
  }
}