{
  "name": "Alan Weber",
  "age": 25,
  "address": {
    "street": "Roji View",
    "city": "Tesvupzu",
    "state": "SC",
    "zip": "88924"
  },
  "contact": {
    "phone": "(325) 698-2819",
    "servicePhone": "800248116"
  },
  "birthday": "1965-07-10T05:04:07.380Z",
  "ip": "17.115.251.37",
  "foo": "bar",
  "profile": {
    "about": "Hi sepew rug tomo vo gigowab anfi cilum onuup asasdeg karmuctif vavejtow olosacu. Ale lirbisiwi gob uta un nalevjot cat idewotjur miegu habo jiwfin hakepwu ogerti sovgosgef tattidcef cetveri jivkejo iwicosid. Gopu etavac puvulma dudbov udhoke pena zecdamoj hekis tihudug hevu pup ciz peuz bipbi ruluis nawamo micpolin. Fuibiaza li jimnecu gimo fejewwi opegiv riwbin ve uzuke no suzagori taszodot gampuhra. Mid dotpe ele ten lecdilof nebdog tojdifki kufum ono fuju veboz kiz fobfe azoko kulimdir oke kabvel.",
    "bio": "Isgeci gelpahe zehzizod dafme rejti epi guzutewe mez rukurji nasfef jur nifor nojpud nihukke tivdi ukbem led. Zewrornat vik efucu sar gesug fozif vam ro monin bit wifik pagilod bawazu kisra udtosic suvakgef sowwetop aho. Higi arlaz gecme fa bigtusmom juc gadof satfu budoh fudus rum naecu sil mawpesdon. Ge gaf dunmew tamife voret absad urkucji ro kanlet tecijfe me ala vidu egu ube eciwi nun. Fo avu gitoh jubempu huzdah eru umive gi nulhovec jil nodeklur tibuhuede mi guzkudil."
  },
  "apiKey": "6ea3d578112a8d8f98443aaaf773ce7e6bef67d3c4882a57ae1cd74cf273a725",
  "currency": {
    "code": "HKD",
    "name": "Hong Kong Dollar"
  }
}